maple_timer/__init__.py
maple_timer/maple_timer.py
maple_timer-1.0.8.dist-info/METADATA
maple_timer-1.0.8.dist-info/WHEEL
maple_timer-1.0.8.dist-info/top_level.txt
maple_timer-1.0.8.dist-info/RECORD
