Metadata-Version: 2.1
Name: maple-timer
Version: 1.0.8
Summary: analysis maple endpoint's performance.
Home-page: https://github.com/dantezhu/maple_timer
Author: dantezhu
Author-email: dantezhu <dantezhu@qq.com>
License: MIT
Project-URL: Homepage, https://github.com/dantezhu/maple_timer
